whl_com.py
whl_com-0.0.3.dist-info/METADATA
whl_com-0.0.3.dist-info/WHEEL
whl_com-0.0.3.dist-info/entry_points.txt
whl_com-0.0.3.dist-info/top_level.txt
whl_com-0.0.3.dist-info/RECORD
