Metadata-Version: 2.4
Name: whl-com
Version: 0.0.3
Summary: config tool for serial devices
Author-email: Pride Leong <lykling.lyk@gmail.com>
Project-URL: Homepage, https://github.com/wheelos-tools/whl-com/tree/main
Project-URL: Bug Tracker, https://github.com/wheelos-tools/whl-com/issues
Requires-Python: >3.8
Requires-Dist: click
Requires-Dist: pyserial
